Workbook

Sheet Como usar
A1: Planilha Grátis de Fechamento de Caixa
B2: Micro no Controle · soluções com sabedoria
B4: Para que serve
B5: Descobrir no mesmo dia se o dinheiro da gaveta bateu, quem estava no caixa quando faltou e quanto isso vira no fim do ano.
B7: Como usar (10 minutos por dia)
B8: 1. Na aba Caixa do Mês, preencha os dados do topo: nome do negócio, mês, tolerância e dias abertos.
B9: 2. Ao fechar o caixa, lance uma linha: data, turno, quem estava no caixa, fundo de troco, vendas em dinheiro, entradas, sangrias e despesas pagas com o dinheiro da gaveta.
B10: 3. Conte a gaveta (de preferência com duas pessoas) e digite o valor em Contado na gaveta.
B11: 4. A planilha mostra o que deveria ter na gaveta, a diferença e a situação: OK, FALTA ou SOBRA.
B12: 5. No fim da semana, abra a aba Resumo: total que faltou, maior falta, diferença por responsável e quanto isso vira em 12 meses.
B14: Regras de ouro
B15: • Só dinheiro físico entra aqui. Cartão e Pix são conferidos com o extrato da maquininha e do banco.
B16: • Toda sangria e toda despesa paga com o caixa precisa de valor, hora e comprovante.
... B25: Funciona no Excel e no Google Sheets (Arquivo → Importar). Estimativas para controle interno; para decisões fiscais, fale com o seu contador.

Sheet Caixa do Mês
A1: FECHAMENTO DE CAIXA — 30 DIAS
A2: Micro no Controle · soluções com sabedoria · micronocontrole.com
A3: Negócio | C3: Meu Restaurante | E3: Células amarelas = você preenche. Brancas = a planilha calcula.
A4: Mês de referência | C4: 46327 | E4: Linha 9 é um exemplo: apague ou escreva por cima.
A5: Tolerância de diferença (R$) | C5: 1
A6: Dias abertos no mês | C6: 26
A8: Data | B8: Turno | C8: Responsável | D8: Fundo de troco | E8: Vendas em dinheiro | F8: Outras entradas | G8: Sangrias | H8: Despesas pagas no caixa | I8: Esperado na gaveta | J8: Contado na gaveta | K8: Diferença | L8: Situação | M8: Observação
A9: 46329 | B9: Noite | C9: Ana | D9: 200 | E9: 1250 | F9: 0 | G9: 800 | H9: 60 | I9: =IF(COUNT(D9:H9)=0,"",N(D9)+N(E9)+N(F9)-N(G9)-N(H9)) -> 590 | J9: 552.5 | K9: =IF(OR(I9="",J9=""),"",J9-I9) -> -37.5 | L9: =IF(K9="","",IF(ABS(K9)<=$C$5,"OK",IF(K9<0,"FALTA","SOBRA"))) -> FALTA | M9: Gelo pago no caixa
I10: =IF(COUNT(D10:H10)=0,"",N(D10)+N(E10)+N(F10)-N(G10)-N(H10)) | K10: =IF(OR(I10="",J10=""),"",J10-I10) | L10: =IF(K10="","",IF(ABS(K10)<=$C$5,"OK",IF(K10<0,"FALTA","SOBRA")))
I11: =IF(COUNT(D11:H11)=0,"",N(D11)+N(E11)+N(F11)-N(G11)-N(H11)) | K11: =IF(OR(I11="",J11=""),"",J11-I11) | L11: =IF(K11="","",IF(ABS(K11)<=$C$5,"OK",IF(K11<0,"FALTA","SOBRA")))
I12: =IF(COUNT(D12:H12)=0,"",N(D12)+N(E12)+N(F12)-N(G12)-N(H12)) | K12: =IF(OR(I12="",J12=""),"",J12-I12) | L12: =IF(K12="","",IF(ABS(K12)<=$C$5,"OK",IF(K12<0,"FALTA","SOBRA")))
I13: =IF(COUNT(D13:H13)=0,"",N(D13)+N(E13)+N(F13)-N(G13)-N(H13)) | K13: =IF(OR(I13="",J13=""),"",J13-I13) | L13: =IF(K13="","",IF(ABS(K13)<=$C$5,"OK",IF(K13<0,"FALTA","SOBRA")))
I14: =IF(COUNT(D14:H14)=0,"",N(D14)+N(E14)+N(F14)-N(G14)-N(H14)) | K14: =IF(OR(I14="",J14=""),"",J14-I14) | L14: =IF(K14="","",IF(ABS(K14)<=$C$5,"OK",IF(K14<0,"FALTA","SOBRA")))
I15: =IF(COUNT(D15:H15)=0,"",N(D15)+N(E15)+N(F15)-N(G15)-N(H15)) | K15: =IF(OR(I15="",J15=""),"",J15-I15) | L15: =IF(K15="","",IF(ABS(K15)<=$C$5,"OK",IF(K15<0,"FALTA","SOBRA")))
I16: =IF(COUNT(D16:H16)=0,"",N(D16)+N(E16)+N(F16)-N(G16)-N(H16)) | K16: =IF(OR(I16="",J16=""),"",J16-I16) | L16: =IF(K16="","",IF(ABS(K16)<=$C$5,"OK",IF(K16<0,"FALTA","SOBRA")))
I17: =IF(COUNT(D17:H17)=0,"",N(D17)+N(E17)+N(F17)-N(G17)-N(H17)) | K17: =IF(OR(I17="",J17=""),"",J17-I17) | L17: =IF(K17="","",IF(ABS(K17)<=$C$5,"OK",IF(K17<0,"FALTA","SOBRA")))
I18: =IF(COUNT(D18:H18)=0,"",N(D18)+N(E18)+N(F18)-N(G18)-N(H18)) | K18: =IF(OR(I18="",J18=""),"",J18-I18) | L18: =IF(K18="","",IF(ABS(K18)<=$C$5,"OK",IF(K18<0,"FALTA","SOBRA")))
I19: =IF(COUNT(D19:H19)=0,"",N(D19)+N(E19)+N(F19)-N(G19)-N(H19)) | K19: =IF(OR(I19="",J19=""),"",J19-I19) | L19: =IF(K19="","",IF(ABS(K19)<=$C$5,"OK",IF(K19<0,"FALTA","SOBRA")))
I20: =IF(COUNT(D20:H20)=0,"",N(D20)+N(E20)+N(F20)-N(G20)-N(H20)) | K20: =IF(OR(I20="",J20=""),"",J20-I20) | L20: =IF(K20="","",IF(ABS(K20)<=$C$5,"OK",IF(K20<0,"FALTA","SOBRA")))
I21: =IF(COUNT(D21:H21)=0,"",N(D21)+N(E21)+N(F21)-N(G21)-N(H21)) | K21: =IF(OR(I21="",J21=""),"",J21-I21) | L21: =IF(K21="","",IF(ABS(K21)<=$C$5,"OK",IF(K21<0,"FALTA","SOBRA")))
... I39: =IF(COUNT(D39:H39)=0,"",N(D39)+N(E39)+N(F39)-N(G39)-N(H39)) | K39: =IF(OR(I39="",J39=""),"",J39-I39) | L39: =IF(K39="","",IF(ABS(K39)<=$C$5,"OK",IF(K39<0,"FALTA","SOBRA")))
A40: TOTAL DO MÊS | E40: =SUM(E9:E39) -> 1250 | F40: =SUM(F9:F39) -> 0 | G40: =SUM(G9:G39) -> 800 | H40: =SUM(H9:H39) -> 60 | K40: =SUM(K9:K39) -> -37.5

Sheet Resumo
A1: RESUMO DO MÊS
A2: ='Caixa do Mês'!C3 -> Meu Restaurante
A4: Dias conferidos | B4: =COUNT('Caixa do Mês'!K9:K39) -> 1
A5: Dias que bateram (OK) | B5: =COUNTIF('Caixa do Mês'!L9:L39,"OK") -> 0
A6: Dias com FALTA | B6: =COUNTIF('Caixa do Mês'!L9:L39,"FALTA") -> 1
A7: Dias com SOBRA | B7: =COUNTIF('Caixa do Mês'!L9:L39,"SOBRA") -> 0
A8: Total que faltou | B8: =SUMIF('Caixa do Mês'!K9:K39,"<0") -> -37.5
A9: Total que sobrou | B9: =SUMIF('Caixa do Mês'!K9:K39,">0") -> 0
A10: Diferença líquida do mês | B10: =SUM('Caixa do Mês'!K9:K39) -> -37.5
A11: Maior falta em um dia | B11: =IF(COUNTIF('Caixa do Mês'!K9:K39,"<0")=0,0,MIN('Caixa do Mês'!K9:K39)) -> -37.5
A12: Diferença média por dia conferido | B12: =IFERROR(SUM('Caixa do Mês'!K9:K39)/COUNT('Caixa do Mês'!K9:K39),0) -> -37.5
A13: Se continuar assim, em 12 meses | B13: =B12*'Caixa do Mês'!C6*12 -> -11700 | C13: Projeção simples: diferença média × dias abertos × 12. Serve de alerta, não de previsão.
A16: DIFERENÇA POR RESPONSÁVEL
A17: Responsável (digite o nome) | B17: Dias no caixa | C17: Diferença somada | D17: Dias com falta
A18: Ana | B18: =IF(A18="","",COUNTIFS('Caixa do Mês'!C9:C39,A18,'Caixa do Mês'!K9:K39,"<>")) -> 1 | C18: =IF(A18="","",SUMIF('Caixa do Mês'!C9:C39,A18,'Caixa do Mês'!K9:K39)) -> -37.5 | D18: =IF(A18="","",COUNTIFS('Caixa do Mês'!C9:C39,A18,'Caixa do Mês'!L9:L39,"FALTA")) -> 1
B19: =IF(A19="","",COUNTIFS('Caixa do Mês'!C9:C39,A19,'Caixa do Mês'!K9:K39,"<>")) | C19: =IF(A19="","",SUMIF('Caixa do Mês'!C9:C39,A19,'Caixa do Mês'!K9:K39)) | D19: =IF(A19="","",COUNTIFS('Caixa do Mês'!C9:C39,A19,'Caixa do Mês'!L9:L39,"FALTA"))
B20: =IF(A20="","",COUNTIFS('Caixa do Mês'!C9:C39,A20,'Caixa do Mês'!K9:K39,"<>")) | C20: =IF(A20="","",SUMIF('Caixa do Mês'!C9:C39,A20,'Caixa do Mês'!K9:K39)) | D20: =IF(A20="","",COUNTIFS('Caixa do Mês'!C9:C39,A20,'Caixa do Mês'!L9:L39,"FALTA"))
B21: =IF(A21="","",COUNTIFS('Caixa do Mês'!C9:C39,A21,'Caixa do Mês'!K9:K39,"<>")) | C21: =IF(A21="","",SUMIF('Caixa do Mês'!C9:C39,A21,'Caixa do Mês'!K9:K39)) | D21: =IF(A21="","",COUNTIFS('Caixa do Mês'!C9:C39,A21,'Caixa do Mês'!L9:L39,"FALTA"))
B22: =IF(A22="","",COUNTIFS('Caixa do Mês'!C9:C39,A22,'Caixa do Mês'!K9:K39,"<>")) | C22: =IF(A22="","",SUMIF('Caixa do Mês'!C9:C39,A22,'Caixa do Mês'!K9:K39)) | D22: =IF(A22="","",COUNTIFS('Caixa do Mês'!C9:C39,A22,'Caixa do Mês'!L9:L39,"FALTA"))
B23: =IF(A23="","",COUNTIFS('Caixa do Mês'!C9:C39,A23,'Caixa do Mês'!K9:K39,"<>")) | C23: =IF(A23="","",SUMIF('Caixa do Mês'!C9:C39,A23,'Caixa do Mês'!K9:K39)) | D23: =IF(A23="","",COUNTIFS('Caixa do Mês'!C9:C39,A23,'Caixa do Mês'!L9:L39,"FALTA"))
A26: Quer conferir também maquininha, contas a pagar, imposto e lucro do mês?
A27: Conheça o Kit Micro no Controle: micronocontrole.com/kit
